dolomite_ranges/__init__.py
dolomite_ranges/read_genomic_ranges.py
dolomite_ranges/read_genomic_ranges_list.py
dolomite_ranges/read_sequence_information.py
dolomite_ranges/save_genomic_ranges.py
dolomite_ranges/save_genomic_ranges_list.py
dolomite_ranges/save_sequence_information.py
dolomite_ranges-0.3.0.dist-info/licenses/LICENSE.txt
dolomite_ranges-0.3.0.dist-info/METADATA
dolomite_ranges-0.3.0.dist-info/WHEEL
dolomite_ranges-0.3.0.dist-info/top_level.txt
dolomite_ranges-0.3.0.dist-info/RECORD
