Metadata-Version: 2.4
Name: dolomite-ranges
Version: 0.3.0
Summary: Stage and load genomic ranges from disk.
Home-page: https://github.com/ArtifactDB/dolomite-ranges
Author: LTLA
Author-email: infinite.monkeys.with.keyboards@gmail.com
License: MIT
Project-URL: Documentation, https://github.com/ArtifactDB/dolomite-ranges
Platform: any
Classifier: Development Status :: 4 - Beta
Classifier: Programming Language :: Python
Requires-Python: >=3.9
License-File: LICENSE.txt
Requires-Dist: importlib-metadata; python_version < "3.8"
Requires-Dist: dolomite-base>=0.4.2
Requires-Dist: genomicranges>=0.8.2
Requires-Dist: biocframe>=0.7.2
Requires-Dist: compressed-lists>=0.4.4
Requires-Dist: h5py
Provides-Extra: testing
Requires-Dist: setuptools; extra == "testing"
Requires-Dist: pytest; extra == "testing"
Requires-Dist: pytest-cov; extra == "testing"
Dynamic: license-file
